mmcterm/__init__.py
mmcterm/__main__.py
mmcterm/mmcterm.py
mmcterm-0.2.1.dist-info/LICENSE.txt
mmcterm-0.2.1.dist-info/METADATA
mmcterm-0.2.1.dist-info/WHEEL
mmcterm-0.2.1.dist-info/entry_points.txt
mmcterm-0.2.1.dist-info/top_level.txt
mmcterm-0.2.1.dist-info/RECORD
