Metadata-Version: 2.1
Name: mmcterm
Version: 0.2.1
Summary: Serial over IPMB terminal for DESY MMCs
Home-page: https://techlab.desy.de
Author: Patrick Huesmann
Author-email: patrick.huesmann@desy.de
License: BSD
Keywords: microtca mmc ipmi ipmb console
Classifier: Programming Language :: Python :: 3.6
Classifier: Operating System :: OS Independent
Classifier: Environment :: Console
Classifier: License :: OSI Approved :: BSD License
Classifier: Intended Audience :: Developers
Classifier: Development Status :: 3 - Alpha
Requires-Python: >=3.6
License-File: LICENSE.txt
Requires-Dist: python-ipmi
